{
  "audit_date": "2026-05-28T21:36:02.497756+00:00",
  "schema": "shared_gdbmdr",
  "phase": "apply",
  "polluted_row_count": 4,
  "rows": [
    {
      "tenant_id": "69688df3-fc8e-51f8-a77c-9c13f9b3a784",
      "entity_id": "finops-demo-co",
      "current_run_id": "f6e97486-fff0-4086-800e-c1e7b69d12e6",
      "current_snapshot_name_old": null,
      "current_snapshot_name_new": "finops-demo-co-f6e9",
      "previous_run_id": "e8a2d1b6-d232-4f67-86b7-d548fe412912",
      "previous_snapshot_name_old": null,
      "previous_snapshot_name_new": "finops-demo-co-e8a2",
      "updated_at": "2026-05-28T17:20:40.453702+00:00"
    },
    {
      "tenant_id": "69688df3-fc8e-51f8-a77c-9c13f9b3a784",
      "entity_id": "r6-verify-co",
      "current_run_id": "76c113dd-7b98-4a08-9abf-19c9e4c8069a",
      "current_snapshot_name_old": null,
      "current_snapshot_name_new": "r6-verify-co-76c1",
      "previous_run_id": null,
      "previous_snapshot_name_old": null,
      "previous_snapshot_name_new": null,
      "updated_at": "2026-05-20T20:41:08.591641+00:00"
    },
    {
      "tenant_id": "69688df3-fc8e-51f8-a77c-9c13f9b3a784",
      "entity_id": "techedge-25kh",
      "current_run_id": "fb544386-42ca-4c8d-837b-849f52e8dd54",
      "current_snapshot_name_old": null,
      "current_snapshot_name_new": "techedge-25kh-fb54",
      "previous_run_id": "f858c037-0e5b-4529-858f-d3ba7e2a1da9",
      "previous_snapshot_name_old": null,
      "previous_snapshot_name_new": "techedge-25kh-f858",
      "updated_at": "2026-05-23T00:59:23.024108+00:00"
    },
    {
      "tenant_id": "69688df3-fc8e-51f8-a77c-9c13f9b3a784",
      "entity_id": "VeloWorks-GQFR",
      "current_run_id": "00000000-1234-5678-9abc-def000000001",
      "current_snapshot_name_old": null,
      "current_snapshot_name_new": "VeloWorks-GQFR-0000",
      "previous_run_id": "fb33d637-9c1f-4cc9-ba0b-0dc73c97b506",
      "previous_snapshot_name_old": "VeloWorks-GQFR-fb33",
      "previous_snapshot_name_new": null,
      "updated_at": "2026-05-14T22:07:14.441984+00:00"
    }
  ]
}